mutable_merkle/__init__.py
mutable_merkle/tree.py
mutable_merkle/util.py
mutable_merkle-0.1.1.dist-info/LICENSE
mutable_merkle-0.1.1.dist-info/WHEEL
mutable_merkle-0.1.1.dist-info/METADATA
mutable_merkle-0.1.1.dist-info/RECORD
