Metadata-Version: 2.1
Name: mutable-merkle
Version: 0.1.1
Summary: A Merkle tree supporting append, update, remove operations.
Home-page: https://github.com/EdgyEdgemond/mutable_merkle/
License: Apache-2.0
Author: Daniel Edgecombe
Author-email: edgy.edgemond@gmail.com
Requires-Python: >=3.5,<4.0
Classifier: License :: OSI Approved :: Apache Software License
Classifier: Programming Language :: Python :: 3
Classifier: Programming Language :: Python :: 3.5
Classifier: Programming Language :: Python :: 3.6
Classifier: Programming Language :: Python :: 3.7
Project-URL: Repository, https://github.com/EdgyEdgemond/mutable_merkle/
